{
  "content_pack_id": "lively_market_town",
  "schema_version": "2.0",
  "world_premise": {
    "era": "medieval_fantasy",
    "tone": "warm_bustling",
    "central_tension": "a thriving market town on the eve of a harvest festival, where rumours travel fast and tempers flare over scarce goods"
  },
  "world_book": [
    {
      "entry_id": "harvest_festival",
      "layer": "canonical_fact",
      "content": "丰收节将至，集市比平日热闹数倍，外来商旅云集。",
      "access": {"visible_to": {"faction": ["all"]}, "hidden_from": {}},
      "confidence_policy": "fact"
    },
    {
      "entry_id": "grain_shortage_rumor",
      "layer": "local_rumor",
      "content": "有人说今年北边歉收，粮价要涨，囤粮的人开始多了。",
      "access": {"visible_to": {"region": ["market_town"]}, "hidden_from": {}},
      "confidence_policy": "belief_not_fact"
    }
  ],
  "starting_location": "market_square",
  "initial_locations": [
    {
      "location_id": "market_square",
      "connections": [
        {"to": "tavern", "distance": "adjacent", "noise_leak": 0.2, "visual_leak": 0.1, "description": "穿过一条挂满灯笼的短巷"},
        {"to": "granary", "distance": "near", "noise_leak": 0.1, "visual_leak": 0.0, "description": "沿石板路向北"}
      ]
    },
    {
      "location_id": "tavern",
      "connections": [
        {"to": "market_square", "distance": "adjacent", "noise_leak": 0.2, "visual_leak": 0.1, "description": "回到喧闹的集市"}
      ]
    },
    {
      "location_id": "granary",
      "connections": [
        {"to": "market_square", "distance": "near", "noise_leak": 0.1, "visual_leak": 0.0, "description": "返回集市中心"}
      ]
    }
  ],
  "initial_entities": [
    {
      "entity_id": "player_001",
      "entity_type": "player",
      "location_id": "market_square",
      "zone_id": "center",
      "attributes": {"strength": 0.5, "dexterity": 0.6, "perception": 0.6, "charisma": 0.55},
      "traits": ["curious", "easygoing"],
      "hp": 100,
      "max_hp": 100,
      "stamina": 100
    },
    {
      "entity_id": "npc.merchant_yan",
      "entity_type": "npc",
      "location_id": "market_square",
      "zone_id": "center",
      "attributes": {"charisma": 0.8, "perception": 0.6},
      "traits": ["talkative", "shrewd", "greedy"]
    },
    {
      "entity_id": "npc.baker_lu",
      "entity_type": "npc",
      "location_id": "market_square",
      "zone_id": "center",
      "attributes": {"charisma": 0.6, "strength": 0.6},
      "traits": ["kind", "gossipy"]
    },
    {
      "entity_id": "npc.guard_ko",
      "entity_type": "npc",
      "location_id": "market_square",
      "zone_id": "center",
      "attributes": {"strength": 0.7, "perception": 0.75},
      "traits": ["watchful", "stern"]
    },
    {
      "entity_id": "npc.ele",
      "entity_type": "npc",
      "location_id": "tavern",
      "zone_id": "main_hall",
      "attributes": {"charisma": 0.8, "perception": 0.7},
      "traits": ["kind", "perceptive"]
    },
    {
      "entity_id": "npc.miller_to",
      "entity_type": "npc",
      "location_id": "granary",
      "zone_id": "store_floor",
      "attributes": {"strength": 0.7, "perception": 0.55},
      "traits": ["anxious", "hardworking"]
    }
  ],
  "initial_relationships": [
    {"npc_id": "npc.merchant_yan", "target_id": "npc.baker_lu", "type": "friendly"},
    {"npc_id": "npc.baker_lu", "target_id": "npc.merchant_yan", "type": "friendly"},
    {"npc_id": "npc.guard_ko", "target_id": "player_001", "type": "wary"},
    {"npc_id": "npc.ele", "target_id": "player_001", "type": "friendly"}
  ],
  "initial_conversations": [],
  "player_agenda_template": {
    "current_drives": [
      {"id": "drive_explore", "label": "逛逛集市，看看有什么新鲜事", "strength": 0.7, "source": "player_declared"}
    ],
    "inference_mode": "reflection_only",
    "suggestion_mode": "subtle"
  },
  "style_guide": {
    "narrative_voice": "第三人称有限视角，聚焦玩家感官体验",
    "tone_references": ["warm_bustling", "warm", "bustling", "grounded"],
    "prohibited_tropes": ["fourth_wall_break", "anachronistic_references"]
  },
  "constraints": {
    "max_entities_per_location": 20,
    "player_death": "incapacitated_only"
  },
  "campaign_drivers": [
    {
      "driver_id": "festival_bustle",
      "type": "social_pressure",
      "description": "集市人多事杂，丰收节前夕摩擦不断。",
      "signals": [
        {"condition": "entity_count >= 5", "weight": 0.5},
        {"condition": "recent_event_count >= 8", "weight": 0.5}
      ],
      "possible_events": [
        {"event_type": "market_haggle_dispute", "probability": 0.4},
        {"event_type": "festival_announcement", "probability": 0.3},
        {"event_type": "grain_price_argument", "probability": 0.3}
      ],
      "severity": 0.4,
      "cooldown_ticks": 6
    }
  ],
  "rule_presets": {
    "difficulty": "normal",
    "stealth_threshold_base": 0.5
  }
}
